<?xml version="1.0" encoding="UTF-8"?>
<list>
<skill id="3700" levels="1" name="Doom Shield">
  <set name="target" val="TARGET_NONE"/>
  <set name="skillType" val="NOTDONE"/>
  <set name="operateType" val="OP_PASSIVE"/>
</skill>
<skill id="3701" levels="1" name="Leather Armor of Doom">
  <set name="target" val="TARGET_NONE"/>
  <set name="skillType" val="NOTDONE"/>
  <set name="operateType" val="OP_PASSIVE"/>
</skill>
<skill id="3702" levels="1" name="Doom Gloves">
  <set name="target" val="TARGET_NONE"/>
  <set name="skillType" val="NOTDONE"/>
  <set name="operateType" val="OP_PASSIVE"/>
</skill>
<skill id="3703" levels="1" name="Doom Boots">
  <set name="target" val="TARGET_NONE"/>
  <set name="skillType" val="NOTDONE"/>
  <set name="operateType" val="OP_PASSIVE"/>
</skill>
<skill id="3704" levels="1" name="Doom Helmet">
  <set name="target" val="TARGET_NONE"/>
  <set name="skillType" val="NOTDONE"/>
  <set name="operateType" val="OP_PASSIVE"/>
</skill>
<skill id="3705" levels="1" name="Doom Gloves">
  <set name="target" val="TARGET_NONE"/>
  <set name="skillType" val="NOTDONE"/>
  <set name="operateType" val="OP_PASSIVE"/>
</skill>
<skill id="3706" levels="1" name="Doom Boots">
  <set name="target" val="TARGET_NONE"/>
  <set name="skillType" val="NOTDONE"/>
  <set name="operateType" val="OP_PASSIVE"/>
</skill>
<skill id="3707" levels="1" name="Tunic of Doom">
  <set name="target" val="TARGET_NONE"/>
  <set name="skillType" val="NOTDONE"/>
  <set name="operateType" val="OP_PASSIVE"/>
</skill>
<skill id="3708" levels="1" name="Stockings of Doom">
  <set name="target" val="TARGET_NONE"/>
  <set name="skillType" val="NOTDONE"/>
  <set name="operateType" val="OP_PASSIVE"/>
</skill>
<skill id="3709" levels="1" name="Doom Helmet">
  <set name="target" val="TARGET_NONE"/>
  <set name="skillType" val="NOTDONE"/>
  <set name="operateType" val="OP_PASSIVE"/>
</skill>
<skill id="3710" levels="1" name="Blue Wolf Breastplate">
  <set name="target" val="TARGET_NONE"/>
  <set name="skillType" val="NOTDONE"/>
  <set name="operateType" val="OP_PASSIVE"/>
</skill>
<skill id="3711" levels="1" name="Blue Wolf Gaiters">
  <set name="target" val="TARGET_NONE"/>
  <set name="skillType" val="NOTDONE"/>
  <set name="operateType" val="OP_PASSIVE"/>
</skill>
<skill id="3712" levels="1" name="Blue Wolf Boots">
  <set name="target" val="TARGET_NONE"/>
  <set name="skillType" val="NOTDONE"/>
  <set name="operateType" val="OP_PASSIVE"/>
</skill>
<skill id="3713" levels="1" name="Blue Wolf Gloves">
  <set name="target" val="TARGET_NONE"/>
  <set name="skillType" val="NOTDONE"/>
  <set name="operateType" val="OP_PASSIVE"/>
</skill>
<skill id="3714" levels="1" name="Blue Wolf Helmet">
  <set name="target" val="TARGET_NONE"/>
  <set name="skillType" val="NOTDONE"/>
  <set name="operateType" val="OP_PASSIVE"/>
</skill>
<skill id="3715" levels="1" name="Blue Wolf Leather Armor">
  <set name="target" val="TARGET_NONE"/>
  <set name="skillType" val="NOTDONE"/>
  <set name="operateType" val="OP_PASSIVE"/>
</skill>
<skill id="3716" levels="1" name="Blue Wolf Boots">
  <set name="target" val="TARGET_NONE"/>
  <set name="skillType" val="NOTDONE"/>
  <set name="operateType" val="OP_PASSIVE"/>
</skill>
<skill id="3717" levels="1" name="Blue Wolf Gloves">
  <set name="target" val="TARGET_NONE"/>
  <set name="skillType" val="NOTDONE"/>
  <set name="operateType" val="OP_PASSIVE"/>
</skill>
<skill id="3718" levels="1" name="Blue Wolf Helmet">
  <set name="target" val="TARGET_NONE"/>
  <set name="skillType" val="NOTDONE"/>
  <set name="operateType" val="OP_PASSIVE"/>
</skill>
<skill id="3719" levels="1" name="Blue Wolf Boots">
  <set name="target" val="TARGET_NONE"/>
  <set name="skillType" val="NOTDONE"/>
  <set name="operateType" val="OP_PASSIVE"/>
</skill>
<skill id="3720" levels="1" name="Blue Wolf Gloves">
  <set name="target" val="TARGET_NONE"/>
  <set name="skillType" val="NOTDONE"/>
  <set name="operateType" val="OP_PASSIVE"/>
</skill>
<skill id="3721" levels="1" name="Blue Wolf Tunic">
  <set name="target" val="TARGET_NONE"/>
  <set name="skillType" val="NOTDONE"/>
  <set name="operateType" val="OP_PASSIVE"/>
</skill>
<skill id="3722" levels="1" name="Blue Wolf Stockings">
  <set name="target" val="TARGET_NONE"/>
  <set name="skillType" val="NOTDONE"/>
  <set name="operateType" val="OP_PASSIVE"/>
</skill>
<skill id="3723" levels="1" name="Blue Wolf Helmet">
  <set name="target" val="TARGET_NONE"/>
  <set name="skillType" val="NOTDONE"/>
  <set name="operateType" val="OP_PASSIVE"/>
</skill>
<skill id="3724" levels="1" name="Dark Crystal Helmet">
  <set name="target" val="TARGET_NONE"/>
  <set name="skillType" val="NOTDONE"/>
  <set name="operateType" val="OP_PASSIVE"/>
</skill>
<skill id="3725" levels="1" name="Dark Crystal Breastplate">
  <set name="target" val="TARGET_NONE"/>
  <set name="skillType" val="NOTDONE"/>
  <set name="operateType" val="OP_PASSIVE"/>
</skill>
<skill id="3726" levels="1" name="Dark Crystal Gaiters">
  <set name="target" val="TARGET_NONE"/>
  <set name="skillType" val="NOTDONE"/>
  <set name="operateType" val="OP_PASSIVE"/>
</skill>
<skill id="3727" levels="1" name="Dark Crystal Gloves">
  <set name="target" val="TARGET_NONE"/>
  <set name="skillType" val="NOTDONE"/>
  <set name="operateType" val="OP_PASSIVE"/>
</skill>
<skill id="3728" levels="1" name="Dark Crystal Boots">
  <set name="target" val="TARGET_NONE"/>
  <set name="skillType" val="NOTDONE"/>
  <set name="operateType" val="OP_PASSIVE"/>
</skill>
<skill id="3729" levels="1" name="Dark Crystal Shield">
  <set name="target" val="TARGET_NONE"/>
  <set name="skillType" val="NOTDONE"/>
  <set name="operateType" val="OP_PASSIVE"/>
</skill>
<skill id="3730" levels="1" name="Dark Crystal Leather Armor">
  <set name="target" val="TARGET_NONE"/>
  <set name="skillType" val="NOTDONE"/>
  <set name="operateType" val="OP_PASSIVE"/>
</skill>
<skill id="3731" levels="1" name="Dark Crystal Gloves">
  <set name="target" val="TARGET_NONE"/>
  <set name="skillType" val="NOTDONE"/>
  <set name="operateType" val="OP_PASSIVE"/>
</skill>
<skill id="3732" levels="1" name="Dark Crystal Boots">
  <set name="target" val="TARGET_NONE"/>
  <set name="skillType" val="NOTDONE"/>
  <set name="operateType" val="OP_PASSIVE"/>
</skill>
<skill id="3733" levels="1" name="Dark Crystal Helmet">
  <set name="target" val="TARGET_NONE"/>
  <set name="skillType" val="NOTDONE"/>
  <set name="operateType" val="OP_PASSIVE"/>
</skill>
<skill id="3734" levels="1" name="Dark Crystal Leggings">
  <set name="target" val="TARGET_NONE"/>
  <set name="skillType" val="NOTDONE"/>
  <set name="operateType" val="OP_PASSIVE"/>
</skill>
<skill id="3735" levels="1" name="Dark Crystal Gloves">
  <set name="target" val="TARGET_NONE"/>
  <set name="skillType" val="NOTDONE"/>
  <set name="operateType" val="OP_PASSIVE"/>
</skill>
<skill id="3736" levels="1" name="Dark Crystal Robe">
  <set name="target" val="TARGET_NONE"/>
  <set name="skillType" val="NOTDONE"/>
  <set name="operateType" val="OP_PASSIVE"/>
</skill>
<skill id="3737" levels="1" name="Dark Crystal Boots">
  <set name="target" val="TARGET_NONE"/>
  <set name="skillType" val="NOTDONE"/>
  <set name="operateType" val="OP_PASSIVE"/>
</skill>
<skill id="3738" levels="1" name="Dark Crystal Helmet">
  <set name="target" val="TARGET_NONE"/>
  <set name="skillType" val="NOTDONE"/>
  <set name="operateType" val="OP_PASSIVE"/>
</skill>
<skill id="3739" levels="1" name="Tallum Gloves">
  <set name="target" val="TARGET_NONE"/>
  <set name="skillType" val="NOTDONE"/>
  <set name="operateType" val="OP_PASSIVE"/>
</skill>
<skill id="3740" levels="1" name="Tallum Boots">
  <set name="target" val="TARGET_NONE"/>
  <set name="skillType" val="NOTDONE"/>
  <set name="operateType" val="OP_PASSIVE"/>
</skill>
<skill id="3741" levels="1" name="Tallum Plate Armor">
  <set name="target" val="TARGET_NONE"/>
  <set name="skillType" val="NOTDONE"/>
  <set name="operateType" val="OP_PASSIVE"/>
</skill>
<skill id="3742" levels="1" name="Tallum Helmet">
  <set name="target" val="TARGET_NONE"/>
  <set name="skillType" val="NOTDONE"/>
  <set name="operateType" val="OP_PASSIVE"/>
</skill>
<skill id="3743" levels="1" name="Tallum Leather Armor">
  <set name="target" val="TARGET_NONE"/>
  <set name="skillType" val="NOTDONE"/>
  <set name="operateType" val="OP_PASSIVE"/>
</skill>
<skill id="3744" levels="1" name="Tallum Gloves">
  <set name="target" val="TARGET_NONE"/>
  <set name="skillType" val="NOTDONE"/>
  <set name="operateType" val="OP_PASSIVE"/>
</skill>
<skill id="3745" levels="1" name="Tallum Boots">
  <set name="target" val="TARGET_NONE"/>
  <set name="skillType" val="NOTDONE"/>
  <set name="operateType" val="OP_PASSIVE"/>
</skill>
<skill id="3746" levels="1" name="Tallum Helmet">
  <set name="target" val="TARGET_NONE"/>
  <set name="skillType" val="NOTDONE"/>
  <set name="operateType" val="OP_PASSIVE"/>
</skill>
<skill id="3747" levels="1" name="Tallum Gloves">
  <set name="target" val="TARGET_NONE"/>
  <set name="skillType" val="NOTDONE"/>
  <set name="operateType" val="OP_PASSIVE"/>
</skill>
<skill id="3748" levels="1" name="Tallum Boots">
  <set name="target" val="TARGET_NONE"/>
  <set name="skillType" val="NOTDONE"/>
  <set name="operateType" val="OP_PASSIVE"/>
</skill>
<skill id="3749" levels="1" name="Tallum Tunic">
  <set name="target" val="TARGET_NONE"/>
  <set name="skillType" val="NOTDONE"/>
  <set name="operateType" val="OP_PASSIVE"/>
</skill>
<skill id="3750" levels="1" name="Tallum Stockings">
  <set name="target" val="TARGET_NONE"/>
  <set name="skillType" val="NOTDONE"/>
  <set name="operateType" val="OP_PASSIVE"/>
</skill>
<skill id="3751" levels="1" name="Tallum Helmet">
  <set name="target" val="TARGET_NONE"/>
  <set name="skillType" val="NOTDONE"/>
  <set name="operateType" val="OP_PASSIVE"/>
</skill>
<skill id="3752" levels="1" name="Majestic Gauntlet">
  <set name="target" val="TARGET_NONE"/>
  <set name="skillType" val="NOTDONE"/>
  <set name="operateType" val="OP_PASSIVE"/>
</skill>
<skill id="3753" levels="1" name="Majestic Circlet">
  <set name="target" val="TARGET_NONE"/>
  <set name="skillType" val="NOTDONE"/>
  <set name="operateType" val="OP_PASSIVE"/>
</skill>
<skill id="3754" levels="1" name="Majestic Plate Armor">
  <set name="target" val="TARGET_NONE"/>
  <set name="skillType" val="NOTDONE"/>
  <set name="operateType" val="OP_PASSIVE"/>
</skill>
<skill id="3755" levels="1" name="Majestic Boots">
  <set name="target" val="TARGET_NONE"/>
  <set name="skillType" val="NOTDONE"/>
  <set name="operateType" val="OP_PASSIVE"/>
</skill>
<skill id="3756" levels="1" name="Majestic Gauntlet">
  <set name="target" val="TARGET_NONE"/>
  <set name="skillType" val="NOTDONE"/>
  <set name="operateType" val="OP_PASSIVE"/>
</skill>
<skill id="3757" levels="1" name="Majestic Leather Armor">
  <set name="target" val="TARGET_NONE"/>
  <set name="skillType" val="NOTDONE"/>
  <set name="operateType" val="OP_PASSIVE"/>
</skill>
<skill id="3758" levels="1" name="Majestic Boots">
  <set name="target" val="TARGET_NONE"/>
  <set name="skillType" val="NOTDONE"/>
  <set name="operateType" val="OP_PASSIVE"/>
</skill>
<skill id="3759" levels="1" name="Majestic Circlet">
  <set name="target" val="TARGET_NONE"/>
  <set name="skillType" val="NOTDONE"/>
  <set name="operateType" val="OP_PASSIVE"/>
</skill>
<skill id="3760" levels="1" name="Majestic Gauntlet">
  <set name="target" val="TARGET_NONE"/>
  <set name="skillType" val="NOTDONE"/>
  <set name="operateType" val="OP_PASSIVE"/>
</skill>
<skill id="3761" levels="1" name="Majestic Robe">
  <set name="target" val="TARGET_NONE"/>
  <set name="skillType" val="NOTDONE"/>
  <set name="operateType" val="OP_PASSIVE"/>
</skill>
<skill id="3762" levels="1" name="Majestic Boots">
  <set name="target" val="TARGET_NONE"/>
  <set name="skillType" val="NOTDONE"/>
  <set name="operateType" val="OP_PASSIVE"/>
</skill>
<skill id="3763" levels="1" name="Majestic Circlet">
  <set name="target" val="TARGET_NONE"/>
  <set name="skillType" val="NOTDONE"/>
  <set name="operateType" val="OP_PASSIVE"/>
</skill>
<skill id="3764" levels="1" name="Armor of Nightmare">
  <set name="target" val="TARGET_NONE"/>
  <set name="skillType" val="NOTDONE"/>
  <set name="operateType" val="OP_PASSIVE"/>
</skill>
<skill id="3765" levels="1" name="Gauntlet of Nightmare">
  <set name="target" val="TARGET_NONE"/>
  <set name="skillType" val="NOTDONE"/>
  <set name="operateType" val="OP_PASSIVE"/>
</skill>
<skill id="3766" levels="1" name="Boots of Nightmare">
  <set name="target" val="TARGET_NONE"/>
  <set name="skillType" val="NOTDONE"/>
  <set name="operateType" val="OP_PASSIVE"/>
</skill>
<skill id="3767" levels="1" name="Helm of Nightmare">
  <set name="target" val="TARGET_NONE"/>
  <set name="skillType" val="NOTDONE"/>
  <set name="operateType" val="OP_PASSIVE"/>
</skill>
<skill id="3768" levels="1" name="Nightmarish Leather Armor">
  <set name="target" val="TARGET_NONE"/>
  <set name="skillType" val="NOTDONE"/>
  <set name="operateType" val="OP_PASSIVE"/>
</skill>
<skill id="3769" levels="1" name="Gauntlet of Nightmare">
  <set name="target" val="TARGET_NONE"/>
  <set name="skillType" val="NOTDONE"/>
  <set name="operateType" val="OP_PASSIVE"/>
</skill>
<skill id="3770" levels="1" name="Boots of Nightmare">
  <set name="target" val="TARGET_NONE"/>
  <set name="skillType" val="NOTDONE"/>
  <set name="operateType" val="OP_PASSIVE"/>
</skill>
<skill id="3771" levels="1" name="Gauntlet of Nightmare">
  <set name="target" val="TARGET_NONE"/>
  <set name="skillType" val="NOTDONE"/>
  <set name="operateType" val="OP_PASSIVE"/>
</skill>
<skill id="3772" levels="1" name="Nightmare Robe">
  <set name="target" val="TARGET_NONE"/>
  <set name="skillType" val="NOTDONE"/>
  <set name="operateType" val="OP_PASSIVE"/>
</skill>
<skill id="3773" levels="1" name="Boots of Nightmare">
  <set name="target" val="TARGET_NONE"/>
  <set name="skillType" val="NOTDONE"/>
  <set name="operateType" val="OP_PASSIVE"/>
</skill>
<skill id="3774" levels="1" name="Shield of Nightmare">
  <set name="target" val="TARGET_NONE"/>
  <set name="skillType" val="NOTDONE"/>
  <set name="operateType" val="OP_PASSIVE"/>
</skill>
<skill id="3775" levels="1" name="Draconic Leather Gloves">
  <set name="target" val="TARGET_NONE"/>
  <set name="skillType" val="NOTDONE"/>
  <set name="operateType" val="OP_PASSIVE"/>
</skill>
<skill id="3776" levels="1" name="Draconic Leather Boots">
  <set name="target" val="TARGET_NONE"/>
  <set name="skillType" val="NOTDONE"/>
  <set name="operateType" val="OP_PASSIVE"/>
</skill>
<skill id="3777" levels="1" name="Draconic Leather Armor">
  <set name="target" val="TARGET_NONE"/>
  <set name="skillType" val="NOTDONE"/>
  <set name="operateType" val="OP_PASSIVE"/>
</skill>
<skill id="3778" levels="1" name="Draconic Leather Helmet">
  <set name="target" val="TARGET_NONE"/>
  <set name="skillType" val="NOTDONE"/>
  <set name="operateType" val="OP_PASSIVE"/>
</skill>
<skill id="3779" levels="1" name="Major Arcana Gloves">
  <set name="target" val="TARGET_NONE"/>
  <set name="skillType" val="NOTDONE"/>
  <set name="operateType" val="OP_PASSIVE"/>
</skill>
<skill id="3780" levels="1" name="Major Arcana Robe">
  <set name="target" val="TARGET_NONE"/>
  <set name="skillType" val="NOTDONE"/>
  <set name="operateType" val="OP_PASSIVE"/>
</skill>
<skill id="3781" levels="1" name="Major Arcana Boots">
  <set name="target" val="TARGET_NONE"/>
  <set name="skillType" val="NOTDONE"/>
  <set name="operateType" val="OP_PASSIVE"/>
</skill>
<skill id="3782" levels="1" name="Major Arcana Circlet">
  <set name="target" val="TARGET_NONE"/>
  <set name="skillType" val="NOTDONE"/>
  <set name="operateType" val="OP_PASSIVE"/>
</skill>
<skill id="3783" levels="1" name="Imperial Crusader Gaiters">
  <set name="target" val="TARGET_NONE"/>
  <set name="skillType" val="NOTDONE"/>
  <set name="operateType" val="OP_PASSIVE"/>
</skill>
<skill id="3784" levels="1" name="Imperial Crusader Gauntlet">
  <set name="target" val="TARGET_NONE"/>
  <set name="skillType" val="NOTDONE"/>
  <set name="operateType" val="OP_PASSIVE"/>
</skill>
<skill id="3785" levels="1" name="Imperial Crusader Boots">
  <set name="target" val="TARGET_NONE"/>
  <set name="skillType" val="NOTDONE"/>
  <set name="operateType" val="OP_PASSIVE"/>
</skill>
<skill id="3786" levels="1" name="Imperial Crusader Shield">
  <set name="target" val="TARGET_NONE"/>
  <set name="skillType" val="NOTDONE"/>
  <set name="operateType" val="OP_PASSIVE"/>
</skill>
<skill id="3787" levels="1" name="Imperial Crusader Helmet">
  <set name="target" val="TARGET_NONE"/>
  <set name="skillType" val="NOTDONE"/>
  <set name="operateType" val="OP_PASSIVE"/>
</skill>
<skill id="3788" levels="1" name="Imperial Crusader Breastplate">
  <set name="target" val="TARGET_NONE"/>
  <set name="skillType" val="NOTDONE"/>
  <set name="operateType" val="OP_PASSIVE"/>
</skill>
<skill id="3789" levels="1" name="Dynasty Breastplate">
  <set name="target" val="TARGET_NONE"/>
  <set name="skillType" val="NOTDONE"/>
  <set name="operateType" val="OP_PASSIVE"/>
</skill>
<skill id="3790" levels="1" name="Dynasty Gaiters">
  <set name="target" val="TARGET_NONE"/>
  <set name="skillType" val="NOTDONE"/>
  <set name="operateType" val="OP_PASSIVE"/>
</skill>
<skill id="3791" levels="1" name="Dynasty Gauntlet">
  <set name="target" val="TARGET_NONE"/>
  <set name="skillType" val="NOTDONE"/>
  <set name="operateType" val="OP_PASSIVE"/>
</skill>
<skill id="3792" levels="1" name="Dynasty Boots">
  <set name="target" val="TARGET_NONE"/>
  <set name="skillType" val="NOTDONE"/>
  <set name="operateType" val="OP_PASSIVE"/>
</skill>
<skill id="3793" levels="1" name="Dynasty Shield">
  <set name="target" val="TARGET_NONE"/>
  <set name="skillType" val="NOTDONE"/>
  <set name="operateType" val="OP_PASSIVE"/>
</skill>
<skill id="3794" levels="1" name="Dynasty Helmet">
  <set name="target" val="TARGET_NONE"/>
  <set name="skillType" val="NOTDONE"/>
  <set name="operateType" val="OP_PASSIVE"/>
</skill>
<skill id="3795" levels="1" name="Dynasty Leather Armor">
  <set name="target" val="TARGET_NONE"/>
  <set name="skillType" val="NOTDONE"/>
  <set name="operateType" val="OP_PASSIVE"/>
</skill>
<skill id="3796" levels="1" name="Dynasty Leather Leggings">
  <set name="target" val="TARGET_NONE"/>
  <set name="skillType" val="NOTDONE"/>
  <set name="operateType" val="OP_PASSIVE"/>
</skill>
<skill id="3797" levels="1" name="Dynasty Leather Boots">
  <set name="target" val="TARGET_NONE"/>
  <set name="skillType" val="NOTDONE"/>
  <set name="operateType" val="OP_PASSIVE"/>
</skill>
<skill id="3798" levels="1" name="Dynasty Leather Helmet">
  <set name="target" val="TARGET_NONE"/>
  <set name="skillType" val="NOTDONE"/>
  <set name="operateType" val="OP_PASSIVE"/>
</skill>
<skill id="3799" levels="1" name="Dynasty Tunic">
  <set name="target" val="TARGET_NONE"/>
  <set name="skillType" val="NOTDONE"/>
  <set name="operateType" val="OP_PASSIVE"/>
</skill>
</list>